archer_tools/__init__.py
archer_tools/archer_tools.py
archer_tools/cli.py
archer_tools/config_schema.py
archer_tools/credential_schema.py
archer_tools/errors.py
archer_tools/remote/__init__.py
archer_tools/remote/archer.py
archer_tools/remote/destination.py
archer_tools/remote/ldap.py
archer_tools/remote/manual.py
archer_tools/remote/source.py
archer_tools/remote/libraries/__init__.py
archer_tools/remote/libraries/ldap_helper.py
archer_tools-0.4.0.dist-info/LICENSE.md
archer_tools-0.4.0.dist-info/METADATA
archer_tools-0.4.0.dist-info/WHEEL
archer_tools-0.4.0.dist-info/entry_points.txt
archer_tools-0.4.0.dist-info/top_level.txt
archer_tools-0.4.0.dist-info/RECORD
